{
	"$schema": "http://schema.management.azure.com/schemas/2015-01-01/deploymentTemplate.json#",
	"contentVersion": "1.0.0.0",
	"parameters": {
		"factoryName": {
			"type": "string",
			"metadata": "Data Factory name",
			"defaultValue": "devdatafactorydemo2"
		},
		"LinkedService_devstr_connectionString": {
			"type": "secureString",
			"metadata": "Secure string for 'connectionString' of 'LinkedService_devstr'"
		}
	},
	"variables": {
		"factoryId": "[concat('Microsoft.DataFactory/factories/', parameters('factoryName'))]"
	},
	"resources": [
		{
			"name": "[concat(parameters('factoryName'), '/LinkedService_devstr')]",
			"type": "Microsoft.DataFactory/factories/linkedServices",
			"apiVersion": "2018-06-01",
			"properties": {
				"annotations": [],
				"type": "AzureBlobStorage",
				"typeProperties": {
					"connectionString": "[parameters('LinkedService_devstr_connectionString')]"
				}
			},
			"dependsOn": []
		},
		{
			"name": "[concat(parameters('factoryName'), '/InputDataset')]",
			"type": "Microsoft.DataFactory/factories/datasets",
			"apiVersion": "2018-06-01",
			"properties": {
				"linkedServiceName": {
					"referenceName": "LinkedService_devstr",
					"type": "LinkedServiceReference"
				},
				"annotations": [],
				"type": "Binary",
				"typeProperties": {
					"location": {
						"type": "AzureBlobStorageLocation",
						"fileName": "details.txt",
						"folderPath": "Input",
						"container": "adfdemo2"
					}
				}
			},
			"dependsOn": [
				"[concat(variables('factoryId'), '/linkedServices/LinkedService_devstr')]"
			]
		},
		{
			"name": "[concat(parameters('factoryName'), '/OutputDataset')]",
			"type": "Microsoft.DataFactory/factories/datasets",
			"apiVersion": "2018-06-01",
			"properties": {
				"linkedServiceName": {
					"referenceName": "LinkedService_devstr",
					"type": "LinkedServiceReference"
				},
				"annotations": [],
				"type": "Binary",
				"typeProperties": {
					"location": {
						"type": "AzureBlobStorageLocation",
						"fileName": "details_copy_4.txt",
						"folderPath": "Output",
						"container": "adfdemo2"
					}
				}
			},
			"dependsOn": [
				"[concat(variables('factoryId'), '/linkedServices/LinkedService_devstr')]"
			]
		},
		{
			"name": "[concat(parameters('factoryName'), '/OutputDataset1')]",
			"type": "Microsoft.DataFactory/factories/datasets",
			"apiVersion": "2018-06-01",
			"properties": {
				"linkedServiceName": {
					"referenceName": "LinkedService_devstr",
					"type": "LinkedServiceReference"
				},
				"annotations": [],
				"type": "Binary",
				"typeProperties": {
					"location": {
						"type": "AzureBlobStorageLocation",
						"fileName": "details_copy2.txt",
						"folderPath": "Output1",
						"container": "adfdemo2"
					}
				}
			},
			"dependsOn": [
				"[concat(variables('factoryId'), '/linkedServices/LinkedService_devstr')]"
			]
		},
		{
			"name": "[concat(parameters('factoryName'), '/pipeline1')]",
			"type": "Microsoft.DataFactory/factories/pipelines",
			"apiVersion": "2018-06-01",
			"properties": {
				"activities": [
					{
						"name": "Copy data1",
						"type": "Copy",
						"dependsOn": [],
						"policy": {
							"timeout": "0.12:00:00",
							"retry": 0,
							"retryIntervalInSeconds": 30,
							"secureOutput": false,
							"secureInput": false
						},
						"userProperties": [],
						"typeProperties": {
							"source": {
								"type": "BinarySource",
								"storeSettings": {
									"type": "AzureBlobStorageReadSettings",
									"recursive": true
								},
								"formatSettings": {
									"type": "BinaryReadSettings"
								}
							},
							"sink": {
								"type": "BinarySink",
								"storeSettings": {
									"type": "AzureBlobStorageWriteSettings"
								}
							},
							"enableStaging": false
						},
						"inputs": [
							{
								"referenceName": "InputDataset",
								"type": "DatasetReference",
								"parameters": {}
							}
						],
						"outputs": [
							{
								"referenceName": "OutputDataset",
								"type": "DatasetReference",
								"parameters": {}
							}
						]
					}
				],
				"policy": {
					"elapsedTimeMetric": {}
				},
				"annotations": [],
				"lastPublishTime": "2024-01-24T08:49:15Z"
			},
			"dependsOn": [
				"[concat(variables('factoryId'), '/datasets/InputDataset')]",
				"[concat(variables('factoryId'), '/datasets/OutputDataset')]"
			]
		},
		{
			"name": "[concat(parameters('factoryName'), '/pipeline2')]",
			"type": "Microsoft.DataFactory/factories/pipelines",
			"apiVersion": "2018-06-01",
			"properties": {
				"activities": [
					{
						"name": "Copy data1",
						"type": "Copy",
						"dependsOn": [],
						"policy": {
							"timeout": "0.12:00:00",
							"retry": 0,
							"retryIntervalInSeconds": 30,
							"secureOutput": false,
							"secureInput": false
						},
						"userProperties": [],
						"typeProperties": {
							"source": {
								"type": "BinarySource",
								"storeSettings": {
									"type": "AzureBlobStorageReadSettings",
									"recursive": true
								},
								"formatSettings": {
									"type": "BinaryReadSettings"
								}
							},
							"sink": {
								"type": "BinarySink",
								"storeSettings": {
									"type": "AzureBlobStorageWriteSettings"
								}
							},
							"enableStaging": false
						},
						"inputs": [
							{
								"referenceName": "InputDataset",
								"type": "DatasetReference",
								"parameters": {}
							}
						],
						"outputs": [
							{
								"referenceName": "OutputDataset1",
								"type": "DatasetReference",
								"parameters": {}
							}
						]
					}
				],
				"policy": {
					"elapsedTimeMetric": {}
				},
				"annotations": [],
				"lastPublishTime": "2024-01-29T08:01:30Z"
			},
			"dependsOn": [
				"[concat(variables('factoryId'), '/datasets/InputDataset')]",
				"[concat(variables('factoryId'), '/datasets/OutputDataset1')]"
			]
		}
	]
}